Workbook

Sheet table_l10n
A1: id | D1: CN | E1: CHT | F1: EN | G1: ES | H1: JA | I1: RU | J1: KO
A2: string key | D2: string | E2: string | F2: string | G2: string | H2: string | I2: string | J2: string
A3: key | B3: 备注1 公式生成 | C3: 备注2 | D3: 简体中文 中文 | E3: 繁體中文 繁体中文 | F3: English 英语 | G3: Español 西班牙语 | H3: 日本語 日语 | I3: Русский 俄语 | J3: 한국어 韩语
A4: carbody_name_100101 | B4: {=_xlfn.TEXTJOIN(,1,IF(IFERROR(FIND(table_prefix[前缀],table_l10n!A4),FALSE),TEXT(table_prefix[说明],""),""))} -> 车体 - 名称 | C4: 简易篷车 | D4: 简易篷车 | E4: =_xlfn.TRANSLATE($D4,"zh-chs","zh-cht") -> 簡易篷車 | F4: =_xlfn.TRANSLATE($D4,"zh-chs","en") -> Improvised caravan | G4: =_xlfn.TRANSLATE($D4,"zh-chs","es") -> Caravana improvisada | H4: =_xlfn.TRANSLATE($D4,"zh-chs","ja") -> 即席キャラバン | I4: =_xlfn.TRANSLATE($D4,"zh-chs","ru") -> Импровизированный караван | J4: =_xlfn.TRANSLATE($D4,"zh-chs","ko") -> 즉석 캐러밴
B5: {=_xlfn.TEXTJOIN(,1,IF(IFERROR(FIND(table_prefix[前缀],table_l10n!A5),FALSE),TEXT(table_prefix[说明],""),""))} | E5: =_xlfn.TRANSLATE($D5,"zh-chs","zh-cht") | F5: =_xlfn.TRANSLATE($D5,"zh-chs","en") | G5: =_xlfn.TRANSLATE($D5,"zh-chs","es") | H5: =_xlfn.TRANSLATE($D5,"zh-chs","ja") | I5: =_xlfn.TRANSLATE($D5,"zh-chs","ru") | J5: =_xlfn.TRANSLATE($D5,"zh-chs","ko")
A6: carbody_name_101101 | B6: {=_xlfn.TEXTJOIN(,1,IF(IFERROR(FIND(table_prefix[前缀],table_l10n!A6),FALSE),TEXT(table_prefix[说明],""),""))} -> 车体 - 名称 | C6: 捕奴囚笼 | D6: 捕奴囚笼 | E6: 捕奴囚籠 | F6: Slave cages | G6: Jaulas de esclavos | H6: スレーブケージ | I6: Вольничьи клетки | J6: 슬레이브 케이지
A7: carbody_name_101102 | B7: {=_xlfn.TEXTJOIN(,1,IF(IFERROR(FIND(table_prefix[前缀],table_l10n!A7),FALSE),TEXT(table_prefix[说明],""),""))} -> 车体 - 名称 | C7: 镇暴装甲 | D7: 镇暴装甲 | E7: 鎮暴裝甲 | F7: Riot Suppression Armor | G7: Armadura de supresión de disturbios | H7: ライオット・サプレッション・アーマー | I7: Броня для подавления беспорядков | J7: 폭동 진압 갑옷
B8: {=_xlfn.TEXTJOIN(,1,IF(IFERROR(FIND(table_prefix[前缀],table_l10n!A8),FALSE),TEXT(table_prefix[说明],""),""))} | E8: =_xlfn.TRANSLATE($D8,"zh-chs","zh-cht") | F8: =_xlfn.TRANSLATE($D8,"zh-chs","en") | G8: =_xlfn.TRANSLATE($D8,"zh-chs","es") | H8: =_xlfn.TRANSLATE($D8,"zh-chs","ja") | I8: =_xlfn.TRANSLATE($D8,"zh-chs","ru") | J8: =_xlfn.TRANSLATE($D8,"zh-chs","ko")
B9: {=_xlfn.TEXTJOIN(,1,IF(IFERROR(FIND(table_prefix[前缀],table_l10n!A9),FALSE),TEXT(table_prefix[说明],""),""))} | E9: =_xlfn.TRANSLATE($D9,"zh-chs","zh-cht") | F9: =_xlfn.TRANSLATE($D9,"zh-chs","en") | G9: =_xlfn.TRANSLATE($D9,"zh-chs","es") | H9: =_xlfn.TRANSLATE($D9,"zh-chs","ja") | I9: =_xlfn.TRANSLATE($D9,"zh-chs","ru") | J9: =_xlfn.TRANSLATE($D9,"zh-chs","ko")
A10: device_name_1210101_wheel_wooden | B10: {=_xlfn.TEXTJOIN(,1,IF(IFERROR(FIND(table_prefix[前缀],table_l10n!A10),FALSE),TEXT(table_prefix[说明],""),""))} -> 设备 - 名称 | C10: 车轮 | D10: 硬木车轮 | E10: 硬木車輪 | F10: Hardwood wheels | G10: Ruedas de madera dura | H10: 広葉樹ホイール | I10: Колеса из твердой древесины | J10: 경재 바퀴
A11: device_name_12101019_wheel_wooden | B11: {=_xlfn.TEXTJOIN(,1,IF(IFERROR(FIND(table_prefix[前缀],table_l10n!A11),FALSE),TEXT(table_prefix[说明],""),""))} -> 设备 - 名称 | C11: 车轮 | D11: 旧木轮 | E11: 舊木輪 | F11: Old wooden wheels | G11: Ruedas antiguas de madera | H11: 古い木製車輪 | I11: Старые деревянные колёса | J11: 오래된 나무 바퀴
A12: device_name_1210102_wheel_track | B12: {=_xlfn.TEXTJOIN(,1,IF(IFERROR(FIND(table_prefix[前缀],table_l10n!A12),FALSE),TEXT(table_prefix[说明],""),""))} -> 设备 - 名称 | C12: 车轮 | D12: 履带 | E12: 履帶 | F12: track | G12: pista | H12: トラック | I12: дорожка | J12: 추적하다
A13: device_name_1211801_wheel_lifebuoy | B13: {=_xlfn.TEXTJOIN(,1,IF(IFERROR(FIND(table_prefix[前缀],table_l10n!A13),FALSE),TEXT(table_prefix[说明],""),""))} -> 设备 - 名称 | C13: 车轮 | D13: 救生圈 | E13: 救生圈 | F13: buoy | G13: boya | H13: ブイ | I13: буй | J13: 부표
A15: device_name_1310101_dagger | B15: {=_xlfn.TEXTJOIN(,1,IF(IFERROR(FIND(table_prefix[前缀],table_l10n!A15),FALSE),TEXT(table_prefix[说明],""),""))} -> 设备 - 名称 | C15: 近战 | D15: 短匕 | E15: 短匕 | F15: Short dagger | G15: Daga corta | H15: ショートダガー | I15: Короткий кинжал | J15: 짧은 단검
A16: device_name_1310102_machete | B16: {=_xlfn.TEXTJOIN(,1,IF(IFERROR(FIND(table_prefix[前缀],table_l10n!A16),FALSE),TEXT(table_prefix[说明],""),""))} -> 设备 - 名称 | C16: 近战 | D16: 砍刀 | E16: 砍刀 | F16: Machetes | G16: Machetes | H16: 山刀 | I16: Мачете | J16: 마체테
A17: device_name_1310103_claymore | B17: {=_xlfn.TEXTJOIN(,1,IF(IFERROR(FIND(table_prefix[前缀],table_l10n!A17),FALSE),TEXT(table_prefix[说明],""),""))} -> 设备 - 名称 | C17: 近战 | D17: 大剑 | E17: 大劍 | F17: Greatsword | G17: Espadón | H17: グレートソード | I17: Двуручный меч | J17: 대검
A18: device_name_1310104_spear | B18: {=_xlfn.TEXTJOIN(,1,IF(IFERROR(FIND(table_prefix[前缀],table_l10n!A18),FALSE),TEXT(table_prefix[说明],""),""))} -> 设备 - 名称 | C18: 近战 | D18: 长矛 | E18: 長矛 | F18: spear | G18: lanza | H18: 槍 | I18: копьё | J18: 창
A19: device_name_1310105_inflatable_stick | B19: {=_xlfn.TEXTJOIN(,1,IF(IFERROR(FIND(table_prefix[前缀],table_l10n!A19),FALSE),TEXT(table_prefix[说明],""),""))} -> 设备 - 名称 | C19: 近战 | D19: 充气球棒 | E19: 充氣球棒 | F19: Inflatable bats | G19: Bates inflables | H19: 膨らませるバット | I19: Надувные биты | J19: 팽창식 배트
A20: device_name_1310106_circlesaw | B20: {=_xlfn.TEXTJOIN(,1,IF(IFERROR(FIND(table_prefix[前缀],table_l10n!A20),FALSE),TEXT(table_prefix[说明],""),""))} -> 设备 - 名称 | C20: 近战 | D20: 圆锯 | E20: 圓鋸 | F20: circular saw | G20: Sierra circular | H20: 丸ノコ | I20: циркулярная пила | J20: 원형톱
A21: device_name_1310107_double_edged_cutter | B21: {=_xlfn.TEXTJOIN(,1,IF(IFERROR(FIND(table_prefix[前缀],table_l10n!A21),FALSE),TEXT(table_prefix[说明],""),""))} -> 设备 - 名称 | C21: 近战 | D21: 双刃铡刀 | E21: 雙刃鍘刀 | F21: Double-edged sword | G21: Espada de doble filo | H21: 両刃の剣 | I21: Палка о двух концах | J21: 양날의 검
A22: device_name_1311101_executioner_baton | B22: {=_xlfn.TEXTJOIN(,1,IF(IFERROR(FIND(table_prefix[前缀],table_l10n!A22),FALSE),TEXT(table_prefix[说明],""),""))} -> 设备 - 名称 | C22: 近战 | D22: 执刑木棍 | E22: 執刑木棍 | F22: Execution sticks | G22: Palos de ejecución | H22: 実行スティック | I22: Палочки для казни | J22: 실행 스틱
... A48: device_name_1330103_catching_flower | B48: {=_xlfn.TEXTJOIN(,1,IF(IFERROR(FIND(table_prefix[前缀],table_l10n!A48),FALSE),TEXT(table_prefix[说明],""),""))} -> 设备 - 名称 | C48: device_9999_hua | D48: 捕兽草 | E48: 捕獸草 | F48: Trapping grass | G48: Atrapar hierba | H48: 草の捕獲 | I48: Ловля травы | J48: 잔디 덫 놓기
A49: device_name_1330104_gyroscope | B49: {=_xlfn.TEXTJOIN(,1,IF(IFERROR(FIND(table_prefix[前缀],table_l10n!A49),FALSE),TEXT(table_prefix[说明],""),""))} -> 设备 - 名称 | D49: 飞针陀螺 | E49: 飛針陀螺 | F49: Flying needle spinner | G49: Girador de agujas voladoras | H49: フライングニードルスピナー | I49: Спиннер с летающей иглой | J49: 플라잉 니들 스피너
A50: device_name_1330106_car_bomb | B50: {=_xlfn.TEXTJOIN(,1,IF(IFERROR(FIND(table_prefix[前缀],table_l10n!A50),FALSE),TEXT(table_prefix[说明],""),""))} -> 设备 - 名称 | C50: 紧急炸药包 | D50: 采矿炸弹 | E50: 採礦炸彈 | F50: Mining bombs | G50: Bombas mineras | H50: 鉱山爆弾 | I50: Минные бомбы | J50: 광산 폭탄
A51: device_name_1330107 | B51: {=_xlfn.TEXTJOIN(,1,IF(IFERROR(FIND(table_prefix[前缀],table_l10n!A51),FALSE),TEXT(table_prefix[说明],""),""))} -> 设备 - 名称 | C51: 黑洞发射器 | D51: 黑洞发射器 | E51: 黑洞發射器 | F51: Black hole emitter | G51: Emisor de agujero negro | H51: ブラックホールエミッター | I51: Излучатель черных дыр | J51: 블랙홀 이미터
A52: device_name_1330108 | B52: {=_xlfn.TEXTJOIN(,1,IF(IFERROR(FIND(table_prefix[前缀],table_l10n!A52),FALSE),TEXT(table_prefix[说明],""),""))} -> 设备 - 名称 | C52: 磁铁 | D52: 磁铁 | E52: 磁鐵 | F52: magnet | G52: imán | H52: 磁石 | I52: магнит | J52: 자석
A53: device_name_1330109 | B53: {=_xlfn.TEXTJOIN(,1,IF(IFERROR(FIND(table_prefix[前缀],table_l10n!A53),FALSE),TEXT(table_prefix[说明],""),""))} -> 设备 - 名称 | C53: 回收者 | D53: 回收者 | E53: 回收者 | F53: Recyclers | G53: Recicladores | H53: リサイクル業者 | I53: Переработчики | J53: 재활용업체
A54: device_name_1330110 | B54: {=_xlfn.TEXTJOIN(,1,IF(IFERROR(FIND(table_prefix[前缀],table_l10n!A54),FALSE),TEXT(table_prefix[说明],""),""))} -> 设备 - 名称 | C54: 大百变怪 | D54: 大百变怪 | E54: 大百變怪 | F54: BigDitto | G54: Grande Cambiable | H54: 大きな異変 | I54: Большие перемены | J54: 큰 메타몽
A55: device_name_1330111 | B55: {=_xlfn.TEXTJOIN(,1,IF(IFERROR(FIND(table_prefix[前缀],table_l10n!A55),FALSE),TEXT(table_prefix[说明],""),""))} -> 设备 - 名称 | C55: 小百变怪 | D55: 小百变怪 | E55: 小百變怪 | F55: SmallDitto | G55: Pequeño Cambiable | H55: 小さな異変 | I55: Маленькие странники | J55: 작은 메타몽
A56: device_name_1330112 | B56: {=_xlfn.TEXTJOIN(,1,IF(IFERROR(FIND(table_prefix[前缀],table_l10n!A56),FALSE),TEXT(table_prefix[说明],""),""))} -> 设备 - 名称 | C56: 气球枪 | D56: 气球枪 | E56: 氣球槍 | F56: Balloon guns | G56: Pistolas de globos | H56: バルーンガン | I56: Аэростатные пушки | J56: 풍선 총
A57: device_name_1330113 | B57: {=_xlfn.TEXTJOIN(,1,IF(IFERROR(FIND(table_prefix[前缀],table_l10n!A57),FALSE),TEXT(table_prefix[说明],""),""))} -> 设备 - 名称 | C57: 铅球枪 | D57: 铅球枪 | E57: 鉛球槍 | F57: Shot gun | G57: Escopeta | H57: ショットガン | I57: Дробовик | J57: 샷 건
A58: device_name_1331801_tesla | B58: {=_xlfn.TEXTJOIN(,1,IF(IFERROR(FIND(table_prefix[前缀],table_l10n!A58),FALSE),TEXT(table_prefix[说明],""),""))} -> 设备 - 名称 | C58: 特斯拉电极 | D58: 特斯拉电极 | E58: 特斯拉電極 | F58: Tesla electrodes | G58: Electrodos de Tesla | H58: テスラ電極 | I58: Электроды Теслы | J58: 테슬라 전극
A60: device_name_1340101_buckler | B60: {=_xlfn.TEXTJOIN(,1,IF(IFERROR(FIND(table_prefix[前缀],table_l10n!A60),FALSE),TEXT(table_prefix[说明],""),""))} -> 设备 - 名称 | C60: 盾牌 | D60: 小圆盾 | E60: 小圓盾 | F60: buckler | G60: escudo | H60: 盾 | I60: небольшой круглый щит | J60: 작은 방패
A61: device_name_1340102_wooden_shield | B61: {=_xlfn.TEXTJOIN(,1,IF(IFERROR(FIND(table_prefix[前缀],table_l10n!A61),FALSE),TEXT(table_prefix[说明],""),""))} -> 设备 - 名称 | C61: 盾牌 | D61: 木盾 | E61: 木盾 | F61: Wooden shield | G61: Escudo de madera | H61: 木製の盾 | I61: Деревянный щит | J61: 나무 방패
A62: device_name_1340103_testudo | B62: {=_xlfn.TEXTJOIN(,1,IF(IFERROR(FIND(table_prefix[前缀],table_l10n!A62),FALSE),TEXT(table_prefix[说明],""),""))} -> 设备 - 名称 | C62: 盾牌 | D62: 长阔盾 | E62: 長闊盾 | F62: Long and broad shields | G62: Escudos largos y anchos | H62: 長くて広いシールド | I62: Длинные и широкие щиты | J62: 길고 넓은 방패
... A73: device_name_1351102_executioner_hookrope | B73: {=_xlfn.TEXTJOIN(,1,IF(IFERROR(FIND(table_prefix[前缀],table_l10n!A73),FALSE),TEXT(table_prefix[说明],""),""))} -> 设备 - 名称 | C73: 钩索 | D73: 执刑人挂钩 | E73: 執刑人掛鉤 | F73: Executioner hook | G73: Gancho de verdugo | H73: エクセキューショナーフック | I73: Крюк палача | J73: 처형자 갈고리
B74: {=_xlfn.TEXTJOIN(,1,IF(IFERROR(FIND(table_prefix[前缀],table_l10n!A74),FALSE),TEXT(table_prefix[说明],""),""))}
A75: device_name_1360101_spear_ram | B75: {=_xlfn.TEXTJOIN(,1,IF(IFERROR(FIND(table_prefix[前缀],table_l10n!A75),FALSE),TEXT(table_prefix[说明],""),""))} -> 设备 - 名称 | C75: 撞角 | D75: 刺矛撞角 | E75: 刺矛撞角 | F75: Spike spear ramming horns | G75: Lanza de púas que embisten cuernos | H75: 角に突き刺さるスパイクスピア | I75: Шиповое копье, таранное рога | J75: 스파이크 창 부딪히는 뿔
A76: device_name_1360102_metal_ram | B76: {=_xlfn.TEXTJOIN(,1,IF(IFERROR(FIND(table_prefix[前缀],table_l10n!A76),FALSE),TEXT(table_prefix[说明],""),""))} -> 设备 - 名称 | C76: 撞角 | D76: 金属铲斗 | E76: 金屬鏟鬥 | F76: Metal buckets | G76: Cubos metálicos | H76: 金属製バケツ | I76: Металлические ведра | J76: 금속 양동이
A77: device_name_1360103_bouncing_mushroom | B77: {=_xlfn.TEXTJOIN(,1,IF(IFERROR(FIND(table_prefix[前缀],table_l10n!A77),FALSE),TEXT(table_prefix[说明],""),""))} -> 设备 - 名称 | C77: 撞角 | D77: 菌菇挡板 | E77: 蘑菇擋板 | F77: Mushroom baffle | G77: Deflector de hongos | H77: マッシュルームバッフル | I77: Грибовидная перегородка | J77: 버섯 배플
A78: device_name_1361801_long_harpoon | B78: {=_xlfn.TEXTJOIN(,1,IF(IFERROR(FIND(table_prefix[前缀],table_l10n!A78),FALSE),TEXT(table_prefix[说明],""),""))} -> 设备 - 名称 | C78: 撞角 | D78: 长柄鱼叉 | E78: 長柄魚叉 | F78: Harpoon | G78: Arpón | H78: 銛 | I78: Гарпун | J78: 작살
B79: {=_xlfn.TEXTJOIN(,1,IF(IFERROR(FIND(table_prefix[前缀],table_l10n!A79),FALSE),TEXT(table_prefix[说明],""),""))}
A80: device_alt_wheel | B80: {=_xlfn.TEXTJOIN(,1,IF(IFERROR(FIND(table_prefix[前缀],table_l10n!A80),FALSE),TEXT(table_prefix[说明],""),""))} -> 设备 - alt信息 | C80: 车轮 | D80: 车轮可以不断收集氮气。<br><br>点击冲刺按钮发动冲刺，冲刺效果受当前氮气量影响，满氮气时冲刺效果达到最大。<br><br>氮气集满后可以累积冲刺点数，以连续发动多次冲刺。此时每次冲刺效果都等同于满氮气冲刺效果。<br><br>提示: 当车子卡在上坡动弹不得时，可以尝试连续使用冲刺技能进行脱困。 | E80: =_xlfn.TRANSLATE($D80,"zh-chs","zh-cht") -> 車輪可以不斷收集氮氣。 <br><br>點擊衝刺按鈕發動衝刺，衝刺效果受當前氮氣量影響，滿氮氣時衝刺效果達到最大。 <br><br>氮氣集滿后可以累積衝刺點數，以連續發動多次衝刺。 此時每次衝刺效果都等同於滿氮氣衝刺效果。 <br><br>提示： 當車子卡在上坡動彈不得時，可以嘗試連續使用衝刺技能進行脫困。 | F80: =_xlfn.TRANSLATE($D80,"zh-chs","en") -> The wheels can constantly collect nitrogen. <br><br>Click the sprint button to start a sprint, the sprint effect is affected by the current nitrogen volume, and the sprint effect is maximized when the nitrogen is full. <br><br>When the nitrogen is full, you can accumulate sprint points to launch multiple sprints in a row. At this point, each sprint effect is equivalent to a full nitrogen sprint effect. <br><br>Tip: When the car is stuck uphill and can't move, you can try to use the sprint skill continuously to get out of trouble. | G80: =_xlfn.TRANSLATE($D80,"zh-chs","es") -> Las ruedas pueden acumular nitrógeno constantemente. <br><br>Haz clic en el botón de sprint para iniciar un sprint, el efecto sprint se ve afectado por el volumen actual de nitrógeno, y el efecto sprint se maximiza cuando el nitrógeno está lleno. <br><br>Cuando el nitrógeno está lleno, puedes acumular puntos de sprint para lanzar varios sprints seguidos. En este punto, cada efecto de sprint equivale a un efecto de sprint completo de nitrógeno. <br><br>Consejo: Cuando el coche esté atascado cuesta arriba y no pueda moverse, puedes intentar usar la habilidad de sprint continuamente para salir de problemas. | H80: =_xlfn.TRANSLATE($D80,"zh-chs","ja") -> 車輪は常に窒素を集めることができます。 ス<br><br>プリントボタンをクリックしてスプリントを開始します。スプリント効果は現在の窒素量に影響され、窒素が満タンになるとスプリント効果が最大化されます。 <br><br>窒素が満タンになると、スプリントポイントを溜めて連続で複数のスプリントをスタートできます。 この時点で、各スプリント効果は完全な窒素スプリント効果に相当します。 <br><br>ヒント:車が坂で動けなくなったら、スプリントスキルを使い続けてトラブルから抜け出すことができます。 | I80: =_xlfn.TRANSLATE($D80,"zh-chs","ru") -> Колёса могут постоянно собирать азот. <br><br>Нажмите кнопку спринта, чтобы начать спринт — эффект спринта зависит от текущего объёма азота, и эффект спринта максимизируется, когда азот заполнен. <br><br>Когда азот заполнен, можно накопить очки спринта для запуска нескольких спринтов подряд. На этом этапе каждый эффект спринта эквивалентен эффекту полного азотного спринта. <br><br>Совет: Когда машина застряла в гору и не может двигаться, можно попробовать использовать навык бега постоянно, чтобы избежать неприятностей. | J80: =_xlfn.TRANSLATE($D80,"zh-chs","ko") -> 바퀴는 지속적으로 질소를 모을 수 있습니다. 스<br><br>프린트 버튼을 클릭하면 스프린트를 시작하고, 스프린트 효과는 현재 질소 부피에 영향을 받고, 질소가 가득 차면 스프린트 효과가 최대화됩니다. <br><br>질소가 가득 차면 스프린트 포인트를 모아 연속으로 여러 스프린트를 시작할 수 있습니다. 이 시점에서 각 스프린트 효과는 완전한 질소 스프린트 효과와 같습니다. <br><br>팁: 차가 언덕길에 멈춰 움직일 수 없을 때, 스프린트 스킬을 계속 사용해 위험에서 벗어날 수 있습니다.
A81: device_alt_melee | B81: {=_xlfn.TEXTJOIN(,1,IF(IFERROR(FIND(table_prefix[前缀],table_l10n!A81),FALSE),TEXT(table_prefix[说明],""),""))} -> 设备 - alt信息 | C81: 近战 | D81: 近战武器可以点击按钮手动切换武器状态。<br><br>[1.攻击状态]: 该状态下会自动攻击周围的敌人，每次攻击会消耗锋利度。<br><br>锋利度降低后，武器伤害会随之降低。<br><br>[2.待机状态]: 该状态下无法攻击敌人，但玩家可以在磨刀石上手动磨砺武器，以恢复武器锋利度。 | E81: 近戰武器可以點擊按鈕手動切換武器狀態。 <br><br>[1.攻擊狀態]： 該狀態下會自動攻擊周圍的敵人，每次攻擊會消耗鋒利度。 <br><br>鋒利度降低后，武器傷害會隨之降低。 <br><br>[2.待機狀態]： 該狀態下無法攻擊敵人，但玩家可以在磨刀石上手動磨礪武器，以恢復武器鋒利度。 | F81: Melee weapons can be manually switched with the click of a button. <br><br>[1. Attack Status]: In this state, it will automatically attack nearby enemies, and each attack will consume sharpness. <br><br>When the sharpness is reduced, the weapon damage is reduced. <br><br>[2. Standby]: This state cannot attack enemies, but the player can manually sharpen their weapons on the whetstone to restore their sharpness. | G81: Las armas cuerpo a cuerpo se pueden cambiar manualmente con solo hacer clic en un botón. <br><br>[1. Estado de ataque]: En este estado, atacará automáticamente a los enemigos cercanos y cada ataque consumirá nitidez. <br><br>Cuando se reduce la nitidez, se reduce el daño del arma. <br><br>[2. Standby]: Este estado no puede atacar a los enemigos, pero el jugador puede afilar manualmente sus armas en la piedra de afilar para restaurar su filo. | H81: 近接武器はボタンをクリックするだけで手動で切り替えることができます。 <br><br>【1.攻撃状態】:この状態では、周囲の敵を自動的に攻撃し、攻撃するたびに斬り気を消費する。 <br><br>斬れが下がると、武器のダメージが減少します。 <br><br>[2.スタンバイ]:この状態では敵を攻撃することはできませんが、プレイヤーは手動で砥石で武器を研ぎ、鋭さを回復することができます。 | I81: Оружие ближнего боя можно переключать вручную одним нажатием кнопки. <br><br>[1. Статус атаки]: В этом состоянии он автоматически атакует ближайших врагов, и каждая атака расходует остроту. <br><br>Когда резкость снижается, урон оружия уменьшается. <br><br>[2. Режим ожидания]: Это состояние не может атаковать врагов, но игрок может вручную заточить свое оружие на точильном камне, чтобы восстановить его остроту. | J81: 근접 무기는 버튼 클릭으로 수동으로 전환할 수 있습니다. <br><br>[1. 공격 상태]: 이 상태에서는 자동으로 주변 적을 공격하며, 공격할 때마다 날카로움을 소모합니다. <br><br>선명도가 감소하면 무기 피해가 감소합니다. <br><br>[2. 대기]: 이 상태는 적을 공격할 수 없지만, 숫돌에서 수동으로 무기를 갈고 날카로움을 회복할 수 있습니다.
A82: device_alt_ranged | B82: {=_xlfn.TEXTJOIN(,1,IF(IFERROR(FIND(table_prefix[前缀],table_l10n!A82),FALSE),TEXT(table_prefix[说明],""),""))} -> 设备 - alt信息 | C82: 远程 | D82: 远程武器攻击前需要手动锁定敌人。拖动准星至敌人身上，松开鼠标即可完成锁定。<br><br>当射程内存在已锁定的敌人时，远程武器会自动向目标射击。<br><br>子弹不足时无法射击，需要手动装填。<br><br>注意: 远程武器存在最小射程限制。 | E82: 遠端武器攻擊前需要手動鎖定敵人。 <br><br>拖動準星至敵人身上，鬆開滑鼠即可完成鎖定。 <br><br>當射程記憶體在已鎖定的敵人時，遠端武器會自動向目標射擊。 <br><br>子彈不足時無法射擊，需要手動裝填。 <br><br>注意： 遠端武器存在最小射程限制。 | F82: Ranged weapons need to manually lock on to enemies before attacking. <br><br>Drag the crosshair over the enemy and release the mouse to lock on. <br><br>When there is a locked enemy within range, the ranged weapon will automatically fire at the target. <br><br>Cannot shoot when running out of bullets, it needs to be reloaded manually. <br><br>Note: There is a minimum range limit for ranged weapons. | G82: Las armas a distancia deben fijarse manualmente a los enemigos antes de atacar. <br><br>Arrastra el punto de mira sobre el enemigo y suelta el ratón para bloquearlo. <br><br>Cuando hay un enemigo bloqueado dentro del alcance, el arma a distancia disparará automáticamente al objetivo. <br><br>No puede disparar cuando se está quedando sin balas, debe recargarse manualmente. <br><br>Nota: Hay un límite mínimo de alcance para las armas a distancia. | H82: 遠隔武器は、攻撃する前に手動で敵をロックオンする必要があります。 <br><br>十字線を敵の上にドラッグし、マウスを離してロックオンします。 <br><br>範囲内にロックされた敵がいると、遠距離武器は自動的にターゲットに向けて発砲します。 <br><br>弾丸がなくなると撃つことができないため、手動で再装填する必要があります。 <br><br>注: 遠隔武器には最低射程制限があります。 | I82: Оружие дальнего боя должно вручную наводиться на врагов перед атакой. <br><br>Наведите прицел на врага и отпустите мышь, чтобы захватить цель. <br><br>Когда в пределах досягаемости находится заблокированный враг, оружие дальнего боя автоматически выстрелит в цель. <br><br>Не может стрелять, когда заканчиваются патроны, его нужно перезаряжать вручную. <br><br>Примечание: Существует минимальный предел дальности стрельбы для оружия дальнего боя. | J82: 원거리 무기는 공격하기 전에 수동으로 적을 조준해야 합니다. <br><br>적 위로 십자선을 드래그하고 마우스를 놓으면 고정됩니다. <br><br>사정거리 내에 잠긴 적이 있을 경우, 원거리 무기가 자동으로 대상을 향해 발사합니다. <br><br>총알이 떨어지면 쏠 수 없으며 수동으로 재장전해야 합니다. <br><br>참고: 원거리 무기에는 최소 사거리 제한이 있습니다.
A83: device_alt_unique | B83: {=_xlfn.TEXTJOIN(,1,IF(IFERROR(FIND(table_prefix[前缀],table_l10n!A83),FALSE),TEXT(table_prefix[说明],""),""))} -> 设备 - alt信息 | C83: 特殊 | D83: 特殊设备效果各异，请自行探索。 | E83: 特殊設備效果各異，請自行探索。 | F83: Special equipment has different effects, so please explore it yourself. | G83: El equipo especial tiene diferentes efectos, así que explóralo tú mismo. | H83: 特殊装備は効果が異なりますので、ぜひご自身で探索してみてください。 | I83: Специальное оборудование имеет разные эффекты, поэтому, пожалуйста, изучите его самостоятельно. | J83: 특수 장비는 효과가 다르기 때문에 직접 탐색해 보세요.
A84: device_alt_shield | B84: {=_xlfn.TEXTJOIN(,1,IF(IFERROR(FIND(table_prefix[前缀],table_l10n!A84),FALSE),TEXT(table_prefix[说明],""),""))} -> 设备 - alt信息 | C84: 盾牌 | D84: 盾牌可以反射敌人射来的子弹。<br><br>拖动准星至某一方向，可以使盾牌开启守护模式，主动守护此处。<br><br>守护模式下的盾牌还可以推开碰到的敌人，不过拥有冷却时间。<br><br>反射子弹及推开敌人均消耗能量，能量不足时盾牌会退出守护模式。 | E84: 盾牌可以反射敵人射來的子彈。 <br><br>拖動準星至某一方向，可以使盾牌開啟守護模式，主動守護此處。 <br><br>守護模式下的盾牌還可以推開碰到的敵人，不過擁有冷卻時間。 <br><br>反射子彈及推開敵人均消耗能量，能量不足時盾牌會退出守護模式。 | F84: The shield reflects bullets fired by enemies. <br><br>Drag the crosshair in a certain direction to turn on the shield and actively guard the area. <br><br>The shield in ward mode can also push away enemies it encounters, but it has a cooldown. <br><br>Reflecting bullets and pushing enemies away consumes energy, and the shield exits wards when energy is low. | G84: El escudo refleja las balas disparadas por los enemigos. <br><br>Arrastre la cruz en una dirección determinada para encender el escudo y proteger activamente el área. <br><br>El escudo en el modo centinela también puede ahuyentar a los enemigos que encuentre, pero tiene un tiempo de reutilización. <br><br>Reflejar las balas y alejar a los enemigos consume energía, y el escudo sale de las salas cuando la energía es baja. | H84: シールドは敵が発射した弾丸を反射します。 <br><br>十字線を特定の方向にドラッグしてシールドをオンにし、エリアを積極的に保護します。 <br><br>ワードモードのシールドは、遭遇した敵を押しのけることもできますが、クールダウンがあります。 <br><br>弾丸を反射して敵を押しのけるとエネルギーが消費され、エネルギーが少なくなるとシールドはワードから出ます。 | I84: Щит отражает пули, выпущенные врагами. <br><br>Перетащите перекрестие в определенном направлении, чтобы включить щит и активно охранять территорию. <br><br>Щит в режиме защиты также может отталкивать врагов, с которыми сталкивается, но у него есть перезарядка. <br><br>Отражение пуль и отталкивание врагов потребляет энергию, а щит выходит из вардов, когда энергия заканчивается. | J84: 방패는 적이 발사한 총알을 반사합니다. <br><br>십자선을 특정 방향으로 드래그하여 방패를 켜고 해당 지역을 적극적으로 보호하세요. <br><br>와드 모드의 방패는 마주치는 적을 밀어낼 수도 있지만 재사용 대기시간이 있습니다. <br><br>총알을 반사하고 적을 밀어내면 에너지가 소모되며, 에너지가 부족할 때 방패가 와드를 빠져나갑니다.
A85: device_alt_hook | B85: {=_xlfn.TEXTJOIN(,1,IF(IFERROR(FIND(table_prefix[前缀],table_l10n!A85),FALSE),TEXT(table_prefix[说明],""),""))} -> 设备 - alt信息 | C85: 钩索 | D85: 攻击前需要手动锁定敌人。拖动准星至敌人身上，松开鼠标即可完成锁定。<br><br>当射程内存在已锁定的敌人时，会自动向目标射击，并尝试钩住目标。<br><br>射出钩索时及钩住敌人时，均会消耗“弹性蓄积量”<br><br>“弹性蓄积量”不足时，钩索无法正常使用。<br><br>手动摇动转轮，可以恢复设备的“弹性蓄积量”。<br><br>提示: 钩索可以快速拆分合体类敌人。 | E85: 攻擊前需要手動鎖定敵人。 拖動準星至敵人身上，鬆開滑鼠即可完成鎖定。 <br><br>當射程記憶體在已鎖定的敵人時，會自動向目標射擊，並嘗試鉤住目標。 <br><br>射出鉤索時及鉤住敵人時，均會消耗“彈性蓄積量”<br><br>“彈性蓄積量”不足時，鉤索無法正常使用。 <br><br>手動搖動轉輪，可以恢復設備的“彈性蓄積量”。 <br><br>提示： 鉤索可以快速拆分合體類敵人。 | F85: You need to manually lock on to the enemy before attacking. Drag the crosshair over the enemy and release the mouse to lock on. <br><br>When there is a locked enemy within range, it will automatically shoot at the target and try to hook the target. <br><br>When shooting a hook or hooking an enemy, it consumes "Elastic Accumulation<br><br>", and if the "Elastic Accumulation" is insufficient, the Hook will not be used properly. <br><br>By shaking the runner by hand, the "elastic volume" of the equipment can be restored. <br><br>Tip: Hooks can quickly split merge-type enemies. | G85: Debes fijar manualmente al enemigo antes de atacar. Arrastra el punto de mira sobre el enemigo y suelta el ratón para bloquearlo. <br><br>Cuando hay un enemigo bloqueado dentro del alcance, disparará automáticamente al objetivo e intentará enganchar al objetivo. <br><br>Al disparar un gancho o enganchar a un enemigo, consume "Acumulación elástica<br><br>", y si la "Acumulación elástica" es insuficiente, el gancho no se usará correctamente. <br><br>Al agitar el corredor con la mano, se puede restaurar el "volumen elástico" del equipo. <br><br>Consejo: Los ganchos pueden dividir rápidamente a los enemigos de tipo fusión. | H85: 攻撃する前に、手動で敵にロックオンする必要があります。 十字線を敵の上にドラッグし、マウスを離してロックオンします。 <br><br>範囲内にロックされた敵がいると、自動的にターゲットを撃ち、ターゲットを引っ掛けようとします。 <br><br>フックを撃ったり敵をフックしたりする際には「エラスティック・アキュムレーション」を消費し、「<br><br>エラスティック・アキュムレーション」が足りないとフックがまともに使えなくなります。 <br><br>ランナーを手で振ることで、機器の「弾性ボリューム」を回復させることができます。 <br><br>ヒント:フックは合体タイプの敵をすばやく分割できます。 | I85: Вам нужно вручную нацелиться на врага перед атакой. Наведите прицел на врага и отпустите мышь, чтобы захватить цель. <br><br>Когда в пределах досягаемости находится заблокированный враг, он автоматически выстрелит в цель и попытается зацепить цель. <br><br>При выстреле в крюк или зацеплении врага он расходует "Упругое накопление<br><br>", и если "Упругого накопления" недостаточно, то крюк не будет использован должным образом. <br><br>Встряхивая бегунок рукой, можно восстановить «эластичный объем» оборудования. <br><br>Совет: Крюки могут быстро раскалывать врагов типа слияния. | J85: 공격하기 전에 수동으로 적을 조준해야 합니다. 적 위로 십자선을 드래그하고 마우스를 놓으면 고정됩니다. <br><br>사정거리 내에 잠긴 적이 있으면 자동으로 목표물을 향해 쏘고 갈고리를 시도합니다. <br><br>훅을 쏘거나 적을 훅할 때는 「탄력 축적」을 소모<br><br>해, 「탄력 축적」이 부족하면 훅을 제대로 사용할 수 없게 됩니다. <br><br>러너를 손으로 흔드는 것으로, 장비의 "탄성 볼륨"을 회복할 수 있습니다. <br><br>팁: 갈고리는 병합 타입의 적을 빠르게 분할할 수 있습니다.
A86: device_alt_ram | B86: {=_xlfn.TEXTJOIN(,1,IF(IFERROR(FIND(table_prefix[前缀],table_l10n!A86),FALSE),TEXT(table_prefix[说明],""),""))} -> 设备 - alt信息 | C86: 撞角 | D86: 撞角可以对正面迎来的敌人造成高额伤害，且这一伤害享受速度加成。<br><br>撞角撞到敌人后方向会发生偏离，最终完全指向正上方。<br><br>玩家可以摇动转轮，以将撞角朝向调整至正确朝向。 | E86: 撞角可以對正面迎來的敵人造成高額傷害，且這一傷害享受速度加成。 <br><br>撞角撞到敵人後方向會發生偏離，最終完全指向正上方。 <br><br>玩家可以搖動轉輪，以將撞角朝向調整至正確朝向。 | F86: Ramming Horns deals high damage to enemies facing them, and this damage is given a speed bonus. <br><br>The angle of collision will deviate from the direction of the enemy after hitting it, and eventually point completely upward. <br><br>The player can shake the wheel to adjust the angle of impact to the correct direction. | G86: Embestida de cuernos inflige mucho daño a los enemigos que se enfrentan a ellos, y este daño recibe una bonificación de velocidad. <br><br>El ángulo de colisión se desviará de la dirección del enemigo después de golpearlo y, finalmente, apuntará completamente hacia arriba. <br><br>El jugador puede agitar la rueda para ajustar el ángulo de impacto en la dirección correcta. | H86: 「角笛の体当たり」は、対峙する敵に高いダメージを与え、このダメージには速度ボーナスが付与されます。 <br><br>衝突角度は、敵に当たった後、敵の方向からずれ、最終的には完全に上を向きます。 <br><br>プレイヤーはホイールを振って、衝撃の角度を正しい方向に調整できます。 | I86: Таранные рога наносят большой урон врагам перед собой, и этот урон дает бонус к скорости. <br><br>Угол столкновения будет отклоняться от направления противника после попадания в него, и в конечном итоге будет направлен полностью вверх. <br><br>Игрок может встряхивать колесо, чтобы отрегулировать угол удара в правильном направлении. | J86: 뿔피리를 들이치면 마주하고 있는 적에게 큰 피해를 입히며, 이 피해는 속도 보너스로 제공됩니다. <br><br>충돌 각도는 적에 부딪힌 후 적의 방향에서 벗어나 결국 완전히 위쪽을 향하게 됩니다. <br><br>플레이어는 휠을 흔들어 충격 각도를 올바른 방향으로 조정할 수 있습니다.
A89: device_tag_1410100 | B89: {=_xlfn.TEXTJOIN(,1,IF(IFERROR(FIND(table_prefix[前缀],table_l10n!A89),FALSE),TEXT(table_prefix[说明],""),""))} -> 设备标签 - 名称 | C89: 车轮 | D89: 车轮 | E89: 車輪 | F89: wheels | G89: ruedas | H89: 車輪 | I89: Колеса | J89: 바퀴
B90: {=_xlfn.TEXTJOIN(,1,IF(IFERROR(FIND(table_prefix[前缀],table_l10n!A90),FALSE),TEXT(table_prefix[说明],""),""))}
A91: device_tag_1420100 | B91: {=_xlfn.TEXTJOIN(,1,IF(IFERROR(FIND(table_prefix[前缀],table_l10n!A91),FALSE),TEXT(table_prefix[说明],""),""))} -> 设备标签 - 名称 | C91: 近战武器 | D91: 近战武器 | E91: 近戰武器 | F91: Melee weapons | G91: Armas cuerpo a cuerpo | H91: 近接武器 | I91: Оружие ближнего боя | J91: 근접 무기
A92: device_tag_1420101 | B92: {=_xlfn.TEXTJOIN(,1,IF(IFERROR(FIND(table_prefix[前缀],table_l10n!A92),FALSE),TEXT(table_prefix[说明],""),""))} -> 设备标签 - 名称 | C92: 刀剑 | D92: 刀剑 | E92: 刀劍 | F92: Swords | G92: Espadas | H92: 刀剣 | I92: Мечи | J92: 칼
A93: device_tag_1420102 | B93: {=_xlfn.TEXTJOIN(,1,IF(IFERROR(FIND(table_prefix[前缀],table_l10n!A93),FALSE),TEXT(table_prefix[说明],""),""))} -> 设备标签 - 名称 | C93: 长矛 | D93: 长矛 | E93: 長矛 | F93: spear | G93: lanza | H93: 槍 | I93: копьё | J93: 창
A94: device_tag_1420103 | B94: {=_xlfn.TEXTJOIN(,1,IF(IFERROR(FIND(table_prefix[前缀],table_l10n!A94),FALSE),TEXT(table_prefix[说明],""),""))} -> 设备标签 - 名称 | C94: 棍棒 | D94: 棍棒 | E94: 棍棒 | F94: cudgel | G94: garrote | H94: 棍棒 | I94: дубина | J94: 곤봉
A95: device_tag_1420104 | B95: {=_xlfn.TEXTJOIN(,1,IF(IFERROR(FIND(table_prefix[前缀],table_l10n!A95),FALSE),TEXT(table_prefix[说明],""),""))} -> 设备标签 - 名称 | C95: 斧钺 | D95: 斧钺 | E95: 斧鉞 | F95: Axe | G95: Hacha | H95: 斧 | I95: Топор | J95: 도끼
B96: {=_xlfn.TEXTJOIN(,1,IF(IFERROR(FIND(table_prefix[前缀],table_l10n!A96),FALSE),TEXT(table_prefix[说明],""),""))}
A97: device_tag_1420200 | B97: {=_xlfn.TEXTJOIN(,1,IF(IFERROR(FIND(table_prefix[前缀],table_l10n!A97),FALSE),TEXT(table_prefix[说明],""),""))} -> 设备标签 - 名称 | C97: 远程武器 | D97: 远程武器 | E97: 遠端武器 | F97: Ranged weapons | G97: Armas a distancia | H97: 遠距離武器 | I97: Оружие дальнего боя | J97: 원거리 무기
A98: device_tag_1420210 | B98: {=_xlfn.TEXTJOIN(,1,IF(IFERROR(FIND(table_prefix[前缀],table_l10n!A98),FALSE),TEXT(table_prefix[说明],""),""))} -> 设备标签 - 名称 | C98: 枪械 | D98: 枪械 | E98: 槍械 | F98: Firearms | G98: Armas | H98: 火器 | I98: Огнестрельного оружия | J98: 총기
A99: device_tag_1420211 | B99: {=_xlfn.TEXTJOIN(,1,IF(IFERROR(FIND(table_prefix[前缀],table_l10n!A99),FALSE),TEXT(table_prefix[说明],""),""))} -> 设备标签 - 名称 | C99: 手枪 | D99: 手枪 | E99: 手槍 | F99: pistol | G99: pistola | H99: ピストル | I99: пистолет | J99: 권총
A100: device_tag_1420212 | B100: {=_xlfn.TEXTJOIN(,1,IF(IFERROR(FIND(table_prefix[前缀],table_l10n!A100),FALSE),TEXT(table_prefix[说明],""),""))} -> 设备标签 - 名称 | C100: 霰弹枪 | D100: 霰弹枪 | E100: 霰彈槍 | F100: shotgun | G100: escopeta | H100: ショットガン | I100: дробовик | J100: 산탄총
A101: device_tag_1420213 | B101: {=_xlfn.TEXTJOIN(,1,IF(IFERROR(FIND(table_prefix[前缀],table_l10n!A101),FALSE),TEXT(table_prefix[说明],""),""))} -> 设备标签 - 名称 | C101: 大型枪械 | D101: 大型枪械 | E101: 大型槍械 | F101: Large firearms | G101: Armas de fuego grandes | H101: 大型銃器 | I101: Крупногабаритное огнестрельное оружие | J101: 대형 총기
A102: device_tag_1420221 | B102: {=_xlfn.TEXTJOIN(,1,IF(IFERROR(FIND(table_prefix[前缀],table_l10n!A102),FALSE),TEXT(table_prefix[说明],""),""))} -> 设备标签 - 名称 | C102: 弓箭 | D102: 弓箭 | E102: 弓箭 | F102: bow and arrow | G102: Arco y flecha | H102: 弓と矢 | I102: лук и стрелы | J102: 활과 화살
A103: device_tag_1420222 | B103: {=_xlfn.TEXTJOIN(,1,IF(IFERROR(FIND(table_prefix[前缀],table_l10n!A103),FALSE),TEXT(table_prefix[说明],""),""))} -> 设备标签 - 名称 | C103: 弩 | D103: 弩 | E103: 弩 | F103: crossbow | G103: ballesta | H103: 石弓 | I103: арбалет | J103: 석궁
B104: {=_xlfn.TEXTJOIN(,1,IF(IFERROR(FIND(table_prefix[前缀],table_l10n!A104),FALSE),TEXT(table_prefix[说明],""),""))}
A105: device_tag_1420300 | B105: {=_xlfn.TEXTJOIN(,1,IF(IFERROR(FIND(table_prefix[前缀],table_l10n!A105),FALSE),TEXT(table_prefix[说明],""),""))} -> 设备标签 - 名称 | C105: 独特设备 | D105: 独特设备 | E105: 獨特設備 | F105: Unique equipment | G105: Equipamiento único | H105: ユニークな機器 | I105: Уникальное оборудование | J105: 특유 장비
B106: {=_xlfn.TEXTJOIN(,1,IF(IFERROR(FIND(table_prefix[前缀],table_l10n!A106),FALSE),TEXT(table_prefix[说明],""),""))}
A107: device_tag_1420400 | B107: {=_xlfn.TEXTJOIN(,1,IF(IFERROR(FIND(table_prefix[前缀],table_l10n!A107),FALSE),TEXT(table_prefix[说明],""),""))} -> 设备标签 - 名称 | C107: 盾牌 | D107: 盾牌 | E107: 盾牌 | F107: shield | G107: escudo | H107: 盾 | I107: щит | J107: 방패
B108: {=_xlfn.TEXTJOIN(,1,IF(IFERROR(FIND(table_prefix[前缀],table_l10n!A108),FALSE),TEXT(table_prefix[说明],""),""))}
A109: device_tag_1420500 | B109: {=_xlfn.TEXTJOIN(,1,IF(IFERROR(FIND(table_prefix[前缀],table_l10n!A109),FALSE),TEXT(table_prefix[说明],""),""))} -> 设备标签 - 名称 | C109: 钩索 | D109: 钩索 | E109: 鉤索 | F109: Hook rope | G109: Cuerda de gancho | H109: フックロープ | I109: Крюковый трос | J109: 훅 로프
B110: {=_xlfn.TEXTJOIN(,1,IF(IFERROR(FIND(table_prefix[前缀],table_l10n!A110),FALSE),TEXT(table_prefix[说明],""),""))}
A111: device_tag_1420600 | B111: {=_xlfn.TEXTJOIN(,1,IF(IFERROR(FIND(table_prefix[前缀],table_l10n!A111),FALSE),TEXT(table_prefix[说明],""),""))} -> 设备标签 - 名称 | C111: 撞角 | D111: 撞角 | E111: 撞角 | F111: Knock angle | G111: Ángulo de detonación | H111: ノック角度 | I111: Угол детонации | J111: 노크 각도
B112: {=_xlfn.TEXTJOIN(,1,IF(IFERROR(FIND(table_prefix[前缀],table_l10n!A112),FALSE),TEXT(table_prefix[说明],""),""))}
A113: device_tag_1430001 | B113: {=_xlfn.TEXTJOIN(,1,IF(IFERROR(FIND(table_prefix[前缀],table_l10n!A113),FALSE),TEXT(table_prefix[说明],""),""))} -> 设备标签 - 名称 | C113: 冷兵器 | D113: 冷兵器 | E113: 冷兵器 | F113: cold weapon | G113: Arma fría | H113: コールドウェポン | I113: холодное оружие | J113: 냉기 병기
A114: device_tag_1430002 | B114: {=_xlfn.TEXTJOIN(,1,IF(IFERROR(FIND(table_prefix[前缀],table_l10n!A114),FALSE),TEXT(table_prefix[说明],""),""))} -> 设备标签 - 名称 | C114: 热兵器 | D114: 热兵器 | E114: 熱兵器 | F114: Thermal weapons | G114: Armas térmicas | H114: 熱兵器 | I114: Тепловое оружие | J114: 열병기
A118: role_15101 | B118: {=_xlfn.TEXTJOIN(,1,IF(IFERROR(FIND(table_prefix[前缀],table_l10n!A118),FALSE),TEXT(table_prefix[说明],""),""))} -> 角色 - 名称 | C118: 阿比盖尔 | D118: 阿比盖尔 | E118: 阿比蓋爾 | F118: Abigail | G118: Abigail | H118: アビゲイル | I118: Камеристка | J118: 애비
A119: role_15102 | B119: {=_xlfn.TEXTJOIN(,1,IF(IFERROR(FIND(table_prefix[前缀],table_l10n!A119),FALSE),TEXT(table_prefix[说明],""),""))} -> 角色 - 名称 | C119: 阿飞 | D119: 阿飞 | E119: 阿飛 | F119: hoodlum | G119: matón | H119: チンピラ | I119: хулиган | J119: 불량배
A120: role_15103 | B120: {=_xlfn.TEXTJOIN(,1,IF(IFERROR(FIND(table_prefix[前缀],table_l10n!A120),FALSE),TEXT(table_prefix[说明],""),""))} -> 角色 - 名称 | C120: 雷锵锵 | D120: 雷锵锵 | E120: 雷鏘鏘 | F120: Thunder clang | G120: Sonido metálico de trueno | H120: 雷鳴 | I120: Лязг грома | J120: 천둥 소리
A121: role_15104 | B121: {=_xlfn.TEXTJOIN(,1,IF(IFERROR(FIND(table_prefix[前缀],table_l10n!A121),FALSE),TEXT(table_prefix[说明],""),""))} -> 角色 - 名称 | C121: 响当当 | D121: 响当当 | E121: 響噹噹 | F121: Big | G121: Grande | H121: 大きい | I121: Большой | J121: 큰
A122: role_15105 | B122: {=_xlfn.TEXTJOIN(,1,IF(IFERROR(FIND(table_prefix[前缀],table_l10n!A122),FALSE),TEXT(table_prefix[说明],""),""))} -> 角色 - 名称 | C122: 漆雕婵 | D122: 漆雕婵 | E122: 漆雕嬋 | F122: Lacquer carving chan | G122: Tallado de laca | H122: 漆彫りちゃん | I122: Чан для резьбы по лаку | J122: 옻나무 조각 짱
A123: role_15106 | B123: {=_xlfn.TEXTJOIN(,1,IF(IFERROR(FIND(table_prefix[前缀],table_l10n!A123),FALSE),TEXT(table_prefix[说明],""),""))} -> 角色 - 名称 | C123: 漆雕墩 | D123: 漆雕墩 | E123: 漆雕墩 | F123: Lacquer carved pier | G123: Muelle tallado en laca | H123: 漆彫りの桟橋 | I123: Лакированная резная простенка | J123: 옻칠 조각 교각
A124: role_15107 | B124: {=_xlfn.TEXTJOIN(,1,IF(IFERROR(FIND(table_prefix[前缀],table_l10n!A124),FALSE),TEXT(table_prefix[说明],""),""))} -> 角色 - 名称 | C124: 工头 | D124: 工头 | E124: 工頭 | F124: foreman | G124: capataz | H124: フォアマン | I124: мастер | J124: 포먼
A125: role_15108 | B125: {=_xlfn.TEXTJOIN(,1,IF(IFERROR(FIND(table_prefix[前缀],table_l10n!A125),FALSE),TEXT(table_prefix[说明],""),""))} -> 角色 - 名称 | C125: 小绿人 | D125: 小绿人 | E125: 小綠人 | F125: Little Green Man | G125: Hombrecito Verde | H125: リトル・グリーンマン | I125: Маленький зеленый человечек | J125: 리틀 그린 맨
A126: role_15109 | B126: {=_xlfn.TEXTJOIN(,1,IF(IFERROR(FIND(table_prefix[前缀],table_l10n!A126),FALSE),TEXT(table_prefix[说明],""),""))} -> 角色 - 名称 | C126: 搞事 | D126: 搞事 | E126: 搞事 | F126: Cause trouble | G126: Causar problemas | H126: トラブルを引き起こす | I126: Причиняйте неприятности | J126: 문제를 일으키다
A127: role_15110 | B127: {=_xlfn.TEXTJOIN(,1,IF(IFERROR(FIND(table_prefix[前缀],table_l10n!A127),FALSE),TEXT(table_prefix[说明],""),""))} -> 角色 - 名称 | C127: 小敏 | D127: 小敏 | E127: 小敏 | F127: Xiao Min | G127: Xiao Min | H127: シャオミン | I127: Сяо Минь | J127: 샤오민
... A149: role_15132 | B149: {=_xlfn.TEXTJOIN(,1,IF(IFERROR(FIND(table_prefix[前缀],table_l10n!A149),FALSE),TEXT(table_prefix[说明],""),""))} -> 角色 - 名称 | C149: 大湖特殊npc | D149: 大湖特殊npc | E149: 大湖特殊npc | F149: Great Lakes Special NPC | G149: NPC especial de los Grandes Lagos | H149: 五大湖特別NPC | I149: Особый NPC «Великие озера» | J149: 오대호 특별 NPC
B151: {=_xlfn.TEXTJOIN(,1,IF(IFERROR(FIND(table_prefix[前缀],table_l10n!A151),FALSE),TEXT(table_prefix[说明],""),""))}
A152: trait_name_16301 | B152: {=_xlfn.TEXTJOIN(,1,IF(IFERROR(FIND(table_prefix[前缀],table_l10n!A152),FALSE),TEXT(table_prefix[说明],""),""))} -> 角色特性 - 名称 | C152: 卑微贱民 | D152: 卑微贱民 | E152: =_xlfn.TRANSLATE($D152,"zh-chs","zh-cht") -> 卑微賤民 | F152: =_xlfn.TRANSLATE($D152,"zh-chs","en") -> Humble and untouchable | G152: =_xlfn.TRANSLATE($D152,"zh-chs","es") -> Humilde e intocable | H152: =_xlfn.TRANSLATE($D152,"zh-chs","ja") -> 謙虚で触れられない存在 | I152: =_xlfn.TRANSLATE($D152,"zh-chs","ru") -> Скромный и недосягаемый | J152: =_xlfn.TRANSLATE($D152,"zh-chs","ko") -> 겸손하고 불가피한 존재
A153: trait_name_16302 | B153: {=_xlfn.TEXTJOIN(,1,IF(IFERROR(FIND(table_prefix[前缀],table_l10n!A153),FALSE),TEXT(table_prefix[说明],""),""))} -> 角色特性 - 名称 | C153: 宇航员 | D153: 宇航员 | E153: 宇航員 | F153: astronauts | G153: Astronautas | H153: 宇宙飛行士 | I153: Астронавты | J153: 우주비행사
A154: trait_name_16303 | B154: {=_xlfn.TEXTJOIN(,1,IF(IFERROR(FIND(table_prefix[前缀],table_l10n!A154),FALSE),TEXT(table_prefix[说明],""),""))} -> 角色特性 - 名称 | C154: 幽闭恐惧 | D154: 幽闭恐惧 | E154: 幽閉恐懼 | F154: Claustrophobia and fear | G154: Claustrofobia y miedo | H154: 閉所恐怖症と恐怖 | I154: Клаустрофобия и страх | J154: 폐소공포증과 두려움
A155: trait_name_16304 | B155: {=_xlfn.TEXTJOIN(,1,IF(IFERROR(FIND(table_prefix[前缀],table_l10n!A155),FALSE),TEXT(table_prefix[说明],""),""))} -> 角色特性 - 名称 | C155: 无法工作 | D155: 无法工作 | E155: 無法工作 | F155: Unable to work | G155: Incapaz de trabajar | H155: 働けない | I155: Не в состоянии работать | J155: 일을 할 수 없게
A156: trait_name_16305 | B156: {=_xlfn.TEXTJOIN(,1,IF(IFERROR(FIND(table_prefix[前缀],table_l10n!A156),FALSE),TEXT(table_prefix[说明],""),""))} -> 角色特性 - 名称 | C156: 骑士大人 | D156: 骑士大人 | E156: 騎士大人 | F156: Lord Knight | G156: Lord Caballero | H156: ロード・ナイト | I156: Лорд Рыцарь | J156: 로드 나이트
A157: trait_name_16306 | B157: {=_xlfn.TEXTJOIN(,1,IF(IFERROR(FIND(table_prefix[前缀],table_l10n!A157),FALSE),TEXT(table_prefix[说明],""),""))} -> 角色特性 - 名称 | C157: 亚当夏娃 | D157: 亚当夏娃 | E157: 亞當夏娃 | F157: Adam and Eve | G157: Adán y Eva | H157: アダムとイブ | I157: Адам и Ева | J157: 아담과 이브
A158: trait_name_16307 | B158: {=_xlfn.TEXTJOIN(,1,IF(IFERROR(FIND(table_prefix[前缀],table_l10n!A158),FALSE),TEXT(table_prefix[说明],""),""))} -> 角色特性 - 名称 | C158: 工坊工匠 | D158: 工坊工匠 | E158: 工坊工匠 | F158: Workshop craftsman | G158: Artesano del taller | H158: 工房職人 | I158: Мастер-мастер | J158: 작업장 장인
A159: trait_name_16308 | B159: {=_xlfn.TEXTJOIN(,1,IF(IFERROR(FIND(table_prefix[前缀],table_l10n!A159),FALSE),TEXT(table_prefix[说明],""),""))} -> 角色特性 - 名称 | C159: 专心搜刮 | D159: 专心搜刮 | E159: 專心搜刮 | F159: Concentrate on looting | G159: Concéntrate en el saqueo | H159: 略奪に集中しろ | I159: Сосредоточьтесь на грабеже | J159: 약탈에 집중하세요
A160: trait_name_16309 | B160: {=_xlfn.TEXTJOIN(,1,IF(IFERROR(FIND(table_prefix[前缀],table_l10n!A160),FALSE),TEXT(table_prefix[说明],""),""))} -> 角色特性 - 名称 | C160: 面目可憎 | D160: 面目可憎 | E160: 面目可憎 | F160: The face is abominable | G160: La cara es abominable | H160: 顔はひどい | I160: Лицо отвратительно | J160: 얼굴이 끔찍하다
A161: trait_name_16310 | B161: {=_xlfn.TEXTJOIN(,1,IF(IFERROR(FIND(table_prefix[前缀],table_l10n!A161),FALSE),TEXT(table_prefix[说明],""),""))} -> 角色特性 - 名称 | C161: 奇行种 | D161: 奇行种 | E161: 奇行種 | F161: Odd breed | G161: Raza extraña | H161: 変わり者 | I161: Странная порода | J161: 이상한 종족
A162: trait_name_16311 | B162: {=_xlfn.TEXTJOIN(,1,IF(IFERROR(FIND(table_prefix[前缀],table_l10n!A162),FALSE),TEXT(table_prefix[说明],""),""))} -> 角色特性 - 名称 | C162: 心神不宁 | D162: 心神不宁 | E162: 心神不寧 | F162: He was restless | G162: Estaba inquieto | H162: 彼は落ち着かなかった | I162: Он был беспокойным | J162: 그는 안절부절못했다
A163: trait_name_16401 | B163: {=_xlfn.TEXTJOIN(,1,IF(IFERROR(FIND(table_prefix[前缀],table_l10n!A163),FALSE),TEXT(table_prefix[说明],""),""))} -> 角色特性 - 名称 | C163: 小偷 | D163: 小偷 | E163: 小偷 | F163: Thief | G163: Ladrón | H163: 泥棒 | I163: Вор | J163: 도둑
A164: trait_name_16402 | B164: {=_xlfn.TEXTJOIN(,1,IF(IFERROR(FIND(table_prefix[前缀],table_l10n!A164),FALSE),TEXT(table_prefix[说明],""),""))} -> 角色特性 - 名称 | C164: 擅长收纳 | D164: 擅长收纳 | E164: 擅長收納 | F164: Good at storage | G164: Bueno almacenando | H164: 収納が得意です | I164: Хорошо хранится | J164: 보관에 능숙합니다
...

Sheet -说明
A1: 前缀 | B1: 说明 | C1: id前缀
A2: carbody_name | B2: 车体 - 名称 | C2: 10
A3: device_name | B3: 设备 - 名称 | C3: 12;13
A4: device_alt | B4: 设备 - alt信息 | C4: —
A5: device_tag | B5: 设备标签 - 名称 | C5: 14
A6: role | B6: 角色 - 名称 | C6: 15
A7: trait_name | B7: 角色特性 - 名称 | C7: 16
A8: trait_desc | B8: 角色特性 - 描述 | C8: 16
A9: relic_name | B9: 遗物 - 名称 | C9: 30
A10: relic_desc | B10: 遗物 - 描述 | C10: 30
A11: world | B11: 世界 - 名称 | C11: 40
A12: scene | B12: 场景 - 名称 | C12: 42
A13: weather_name | B13: 天气 - 名称 | C13: 46
A14: weather_desc | B14: 天气 - 描述 | C14: 46
A15: loot_name | B15: 物品 - 名称 | C15: 60
A16: loot_desc | B16: 物品 - 描述 | C16: 60
A17: camp_res_name | B17: 营地资源 - 名称 | C17: 61
A18: dv_upgd_name | B18: 设备升级 - 名称 | C18: 62;63
A19: dv_upgd_desc | B19: 设备升级 - 描述 | C19: 62;63
A20: dv_upgd_story | B20: 设备升级 - 设定 | C20: 62;63
A21: safe_zone | B21: 安全区 | C21: —
A22: tech_name | B22: 科技 - 名称 | C22: 65
A23: tech_desc | B23: 科技 - 描述 | C23: 65
